sendgrid_sdk
