Metadata-Version: 1.0
Name: sendgrid-sdk-python
Version: 0.0.2
Summary: A Python wrapper for the SendGrid API.
Home-page: UNKNOWN
Author: Atte Valtonen
Author-email: atte.valtonen@singa.com
License: MIT
Platform: UNKNOWN
